{
  "description": "Project-scope global variable definitions accessible to all entities. Synchronized with ComponentsParameters.json (28 component types, 131 parameters)",
  "lastModified": "2026-04-06T12:00:00Z",
  "name": "Global Blackboard Register",
  "schema_version": 2,
  "variables": [
    {
      "description": "Current game elapsed time (seconds) since session start",
      "isPersistent": true,
      "key": "gameTime",
      "type": "Float",
      "value": 0
    },
    {
      "description": "Frame delta time in seconds (approximately 1/60th for 60 FPS)",
      "isPersistent": false,
      "key": "deltaTime",
      "type": "Float",
      "value": 0.016
    },
    {
      "description": "Global game pause state affecting all entities",
      "isPersistent": true,
      "key": "isPaused",
      "type": "Bool",
      "value": false
    },
    {
      "description": "Global time scale multiplier (0.5 = half speed, 2.0 = double speed)",
      "isPersistent": false,
      "key": "timeScale",
      "type": "Float",
      "value": 1
    },
    {
      "description": "Game difficulty level (0=Easy, 1=Normal, 2=Hard, 3=Nightmare)",
      "isPersistent": true,
      "key": "difficulty",
      "type": "Int",
      "value": 1
    },
    {
      "description": "Global ambient lighting multiplier (0.0-2.0)",
      "isPersistent": false,
      "key": "ambientLight",
      "type": "Float",
      "value": 1
    },
    {
      "description": "Global gravity acceleration (units/second²)",
      "isPersistent": true,
      "key": "gravity",
      "type": "Float",
      "value": 9.81
    },
    {
      "description": "Global wind force intensity (0.0-1.0+)",
      "isPersistent": false,
      "key": "windStrength",
      "type": "Float",
      "value": 0
    },
    {
      "description": "Current weather condition (clear, rain, snow, fog, storm)",
      "isPersistent": true,
      "key": "weatherType",
      "type": "String",
      "value": "clear"
    },
    {
      "description": "Current time in 24-hour format (0.0-24.0, 12.0=noon, 0.0=midnight)",
      "isPersistent": true,
      "key": "timeOfDay",
      "type": "Float",
      "value": 12
    },
    {
      "description": "Master audio volume level (0.0-1.0)",
      "isPersistent": true,
      "key": "soundVolume",
      "type": "Float",
      "value": 0.8
    },
    {
      "description": "Background music volume level (0.0-1.0)",
      "isPersistent": true,
      "key": "musicVolume",
      "type": "Float",
      "value": 0.6
    },
    {
      "description": "Sound effects volume level (0.0-1.0)",
      "isPersistent": true,
      "key": "effectsVolume",
      "type": "Float",
      "value": 0.8
    },
    {
      "description": "Toggle debug mode on/off across entire game",
      "isPersistent": false,
      "key": "isDebugMode",
      "type": "Bool",
      "value": false
    },
    {
      "description": "Render collision shapes for debugging purposes",
      "isPersistent": false,
      "key": "debugDrawColliders",
      "type": "Bool",
      "value": false
    },
    {
      "description": "Display FPS counter on screen",
      "isPersistent": false,
      "key": "debugShowFPS",
      "type": "Bool",
      "value": false
    },
    {
      "description": "[Identity_data] Entity name identifier",
      "isPersistent": true,
      "key": "entityName",
      "type": "String",
      "value": "Entity"
    },
    {
      "description": "[Identity_data] Entity tag for categorization",
      "isPersistent": true,
      "key": "entityTag",
      "type": "String",
      "value": "Untagged"
    },
    {
      "description": "[Identity_data] Entity type classification",
      "isPersistent": true,
      "key": "entityType",
      "type": "String",
      "value": "UnknownType"
    },
    {
      "description": "[Identity_data] Entity type enumeration",
      "isPersistent": true,
      "key": "entityTypeEnum",
      "type": "String",
      "value": "None"
    },
    {
      "description": "[Position_data] Entity position in world space",
      "isPersistent": true,
      "key": "position",
      "type": "Vector",
      "value": {
        "x": 0,
        "y": 0,
        "z": 0
      }
    },
    {
      "description": "[BoundingBox_data] Bounding box X coordinate",
      "isPersistent": false,
      "key": "bbX",
      "type": "Float",
      "value": 0
    },
    {
      "description": "[BoundingBox_data] Bounding box Y coordinate",
      "isPersistent": false,
      "key": "bbY",
      "type": "Float",
      "value": 0
    },
    {
      "description": "[BoundingBox_data] Bounding box width",
      "isPersistent": false,
      "key": "bbWidth",
      "type": "Float",
      "value": 25
    },
    {
      "description": "[BoundingBox_data] Bounding box height",
      "isPersistent": false,
      "key": "bbHeight",
      "type": "Float",
      "value": 25
    },
    {
      "description": "[TriggerZone_data] Trigger zone radius",
      "isPersistent": false,
      "key": "triggerRadius",
      "type": "Float",
      "value": 15
    },
    {
      "description": "[TriggerZone_data] Trigger zone activation state",
      "isPersistent": false,
      "key": "triggerActivated",
      "type": "Bool",
      "value": false
    },
    {
      "description": "[Movement_data] Entity movement direction",
      "isPersistent": false,
      "key": "movementDirection",
      "type": "Vector",
      "value": {
        "x": 0,
        "y": 0,
        "z": 0
      }
    },
    {
      "description": "[Movement_data] Entity velocity vector",
      "isPersistent": false,
      "key": "movementVelocity",
      "type": "Vector",
      "value": {
        "x": 0,
        "y": 0,
        "z": 0
      }
    },
    {
      "description": "[PhysicsBody_data] Entity body mass (kg)",
      "isPersistent": true,
      "key": "bodyMass",
      "type": "Float",
      "value": 1
    },
    {
      "description": "[PhysicsBody_data] Entity movement speed",
      "isPersistent": false,
      "key": "bodySpeed",
      "type": "Float",
      "value": 150
    },
    {
      "description": "[PhysicsBody_data] Entity friction coefficient",
      "isPersistent": false,
      "key": "bodyFriction",
      "type": "Float",
      "value": 0.1
    },
    {
      "description": "[PhysicsBody_data] Enable gravity on entity",
      "isPersistent": true,
      "key": "bodyUseGravity",
      "type": "Bool",
      "value": true
    },
    {
      "description": "[PhysicsBody_data] Enable rotation physics",
      "isPersistent": true,
      "key": "bodyRotation",
      "type": "Bool",
      "value": false
    },
    {
      "description": "[Health_data] Entity current health points",
      "isPersistent": false,
      "key": "entityCurrentHealth",
      "type": "Int",
      "value": 100
    },
    {
      "description": "[Health_data] Entity maximum health capacity",
      "isPersistent": true,
      "key": "entityMaxHealth",
      "type": "Int",
      "value": 100
    },
    {
      "description": "[AIBehavior_data] Entity behavior type",
      "isPersistent": false,
      "key": "behaviorType",
      "type": "String",
      "value": "idle"
    },
    {
      "description": "[Inventory_data] Entity inventory items (serialized)",
      "isPersistent": true,
      "key": "inventoryItems",
      "type": "String",
      "value": "[]"
    },
    {
      "description": "[VisualSprite_data] Sprite source rect X",
      "isPersistent": false,
      "key": "spriteRectX",
      "type": "Float",
      "value": 0
    },
    {
      "description": "[VisualSprite_data] Sprite source rect Y",
      "isPersistent": false,
      "key": "spriteRectY",
      "type": "Float",
      "value": 0
    },
    {
      "description": "[VisualSprite_data] Sprite source rect width",
      "isPersistent": false,
      "key": "spriteRectWidth",
      "type": "Float",
      "value": 25
    },
    {
      "description": "[VisualSprite_data] Sprite source rect height",
      "isPersistent": false,
      "key": "spriteRectHeight",
      "type": "Float",
      "value": 25
    },
    {
      "description": "[VisualSprite_data] Sprite texture path",
      "isPersistent": true,
      "key": "spritePath",
      "type": "String",
      "value": ""
    },
    {
      "description": "[VisualSprite_data] Sprite hotspot position",
      "isPersistent": false,
      "key": "spriteHotspot",
      "type": "Vector",
      "value": {
        "x": 0,
        "y": 0,
        "z": 0
      }
    },
    {
      "description": "[VisualSprite_data] Sprite color tint (hex)",
      "isPersistent": false,
      "key": "spriteColor",
      "type": "String",
      "value": "#FFFFFF"
    },
    {
      "description": "[VisualSprite_data] Sprite visibility state",
      "isPersistent": false,
      "key": "spriteVisible",
      "type": "Bool",
      "value": true
    },
    {
      "description": "[VisualEditor_data] Editor sprite rect X",
      "isPersistent": false,
      "key": "editorSpriteRectX",
      "type": "Float",
      "value": 0
    },
    {
      "description": "[VisualEditor_data] Editor sprite rect Y",
      "isPersistent": false,
      "key": "editorSpriteRectY",
      "type": "Float",
      "value": 0
    },
    {
      "description": "[VisualEditor_data] Editor sprite rect width",
      "isPersistent": false,
      "key": "editorSpriteRectWidth",
      "type": "Float",
      "value": 25
    },
    {
      "description": "[VisualEditor_data] Editor sprite rect height",
      "isPersistent": false,
      "key": "editorSpriteRectHeight",
      "type": "Float",
      "value": 25
    },
    {
      "description": "[VisualEditor_data] Editor sprite texture path",
      "isPersistent": true,
      "key": "editorSpritePath",
      "type": "String",
      "value": ""
    },
    {
      "description": "[VisualEditor_data] Editor sprite hotspot",
      "isPersistent": false,
      "key": "editorSpriteHotspot",
      "type": "Vector",
      "value": {
        "x": 0,
        "y": 0,
        "z": 0
      }
    },
    {
      "description": "[VisualEditor_data] Editor sprite color",
      "isPersistent": false,
      "key": "editorSpriteColor",
      "type": "String",
      "value": "#FFFFFF"
    },
    {
      "description": "[VisualEditor_data] Editor sprite selection state",
      "isPersistent": false,
      "key": "editorSpriteSelected",
      "type": "Bool",
      "value": false
    },
    {
      "description": "[VisualEditor_data] Editor sprite visibility",
      "isPersistent": false,
      "key": "editorSpriteVisible",
      "type": "Bool",
      "value": true
    },
    {
      "description": "[Animation_data] Animation state ID",
      "isPersistent": false,
      "key": "animationID",
      "type": "String",
      "value": ""
    },
    {
      "description": "[Animation_data] Current animation frame",
      "isPersistent": false,
      "key": "animationFrame",
      "type": "Int",
      "value": 0
    },
    {
      "description": "[Animation_data] Animation frame duration",
      "isPersistent": false,
      "key": "animationFrameDuration",
      "type": "Float",
      "value": 0.1
    },
    {
      "description": "[Animation_data] Animation elapsed time",
      "isPersistent": false,
      "key": "animationElapsedTime",
      "type": "Float",
      "value": 0
    },
    {
      "description": "[VisualAnimation_data] Animation bank ID",
      "isPersistent": false,
      "key": "visualAnimBankId",
      "type": "String",
      "value": ""
    },
    {
      "description": "[VisualAnimation_data] Current animation name",
      "isPersistent": false,
      "key": "visualAnimName",
      "type": "String",
      "value": ""
    },
    {
      "description": "[VisualAnimation_data] Animation graph path",
      "isPersistent": true,
      "key": "visualAnimGraphPath",
      "type": "String",
      "value": ""
    },
    {
      "description": "[VisualAnimation_data] Animation current frame",
      "isPersistent": false,
      "key": "visualAnimFrame",
      "type": "Int",
      "value": 0
    },
    {
      "description": "[VisualAnimation_data] Animation frame timer",
      "isPersistent": false,
      "key": "visualAnimFrameTimer",
      "type": "Float",
      "value": 0
    },
    {
      "description": "[VisualAnimation_data] Animation playback speed multiplier",
      "isPersistent": false,
      "key": "visualAnimPlaybackSpeed",
      "type": "Float",
      "value": 1
    },
    {
      "description": "[VisualAnimation_data] Animation playback state",
      "isPersistent": false,
      "key": "visualAnimIsPlaying",
      "type": "Bool",
      "value": true
    },
    {
      "description": "[VisualAnimation_data] Animation pause state",
      "isPersistent": false,
      "key": "visualAnimIsPaused",
      "type": "Bool",
      "value": false
    },
    {
      "description": "[VisualAnimation_data] Animation loop mode",
      "isPersistent": false,
      "key": "visualAnimLoop",
      "type": "Bool",
      "value": true
    },
    {
      "description": "[VisualAnimation_data] Flip sprite horizontally",
      "isPersistent": false,
      "key": "visualAnimFlipX",
      "type": "Bool",
      "value": false
    },
    {
      "description": "[VisualAnimation_data] Flip sprite vertically",
      "isPersistent": false,
      "key": "visualAnimFlipY",
      "type": "Bool",
      "value": false
    },
    {
      "description": "[VisualAnimation_data] Animation finish flag",
      "isPersistent": false,
      "key": "visualAnimJustFinished",
      "type": "Bool",
      "value": false
    },
    {
      "description": "[VisualAnimation_data] Animation loop count",
      "isPersistent": false,
      "key": "visualAnimLoopCount",
      "type": "Int",
      "value": 0
    },
    {
      "description": "[FX_data] Visual effect type",
      "isPersistent": false,
      "key": "effectType",
      "type": "String",
      "value": ""
    },
    {
      "description": "[FX_data] Effect duration in seconds",
      "isPersistent": false,
      "key": "effectDuration",
      "type": "Float",
      "value": 1
    },
    {
      "description": "[FX_data] Effect elapsed time",
      "isPersistent": false,
      "key": "effectElapsedTime",
      "type": "Float",
      "value": 0
    },
    {
      "description": "[AudioSource_data] Sound effect ID/Path",
      "isPersistent": false,
      "key": "soundEffectID",
      "type": "String",
      "value": ""
    },
    {
      "description": "[AudioSource_data] Sound playback volume (0.0-1.0)",
      "isPersistent": false,
      "key": "soundPlayVolume",
      "type": "Float",
      "value": 1
    },
    {
      "description": "[Controller_data] Controller ID index",
      "isPersistent": false,
      "key": "controllerID",
      "type": "Int",
      "value": -1
    },
    {
      "description": "[Controller_data] Controller connection state",
      "isPersistent": false,
      "key": "controllerConnected",
      "type": "Bool",
      "value": false
    },
    {
      "description": "[Controller_data] Left stick position",
      "isPersistent": false,
      "key": "controllerLeftStick",
      "type": "Vector",
      "value": {
        "x": 0,
        "y": 0,
        "z": 0
      }
    },
    {
      "description": "[Controller_data] Right stick position",
      "isPersistent": false,
      "key": "controllerRightStick",
      "type": "Vector",
      "value": {
        "x": 0,
        "y": 0,
        "z": 0
      }
    },
    {
      "description": "[Controller_data] Left trigger analog value",
      "isPersistent": false,
      "key": "controllerLeftTrigger",
      "type": "Float",
      "value": 0
    },
    {
      "description": "[Controller_data] Right trigger analog value",
      "isPersistent": false,
      "key": "controllerRightTrigger",
      "type": "Float",
      "value": 0
    },
    {
      "description": "[Controller_data] Controller vibration state",
      "isPersistent": false,
      "key": "controllerIsVibrating",
      "type": "Bool",
      "value": false
    },
    {
      "description": "[Controller_data] Controller vibration strength",
      "isPersistent": false,
      "key": "controllerVibrateStrength",
      "type": "Float",
      "value": 0
    },
    {
      "description": "[PlayerController_data] Joystick input direction",
      "isPersistent": false,
      "key": "playerJoystickDirection",
      "type": "Vector",
      "value": {
        "x": 0,
        "y": 0,
        "z": 0
      }
    },
    {
      "description": "[PlayerController_data] Jump input state",
      "isPersistent": false,
      "key": "playerIsJumping",
      "type": "Bool",
      "value": false
    },
    {
      "description": "[PlayerController_data] Shoot input state",
      "isPersistent": false,
      "key": "playerIsShooting",
      "type": "Bool",
      "value": false
    },
    {
      "description": "[PlayerController_data] Walk animation state",
      "isPersistent": false,
      "key": "playerIsWalking",
      "type": "Bool",
      "value": false
    },
    {
      "description": "[PlayerController_data] Run animation state",
      "isPersistent": false,
      "key": "playerIsRunning",
      "type": "Bool",
      "value": false
    },
    {
      "description": "[PlayerController_data] Interaction input state",
      "isPersistent": false,
      "key": "playerIsInteracting",
      "type": "Bool",
      "value": false
    },
    {
      "description": "[PlayerController_data] Item usage state",
      "isPersistent": false,
      "key": "playerIsUsingItem",
      "type": "Bool",
      "value": false
    },
    {
      "description": "[PlayerController_data] Menu open state",
      "isPersistent": false,
      "key": "playerIsMenuOpen",
      "type": "Bool",
      "value": false
    },
    {
      "description": "[PlayerBinding_data] Player index assignment",
      "isPersistent": true,
      "key": "playerIndex",
      "type": "Int",
      "value": 0
    },
    {
      "description": "[PlayerBinding_data] Bound controller ID",
      "isPersistent": false,
      "key": "playerBoundControllerID",
      "type": "Int",
      "value": -1
    },
    {
      "description": "[NPC_data] NPC type classification",
      "isPersistent": true,
      "key": "npcType",
      "type": "String",
      "value": ""
    },
    {
      "description": "[InputMapping_data] Joystick deadzone threshold",
      "isPersistent": true,
      "key": "inputDeadzone",
      "type": "Float",
      "value": 0.15
    },
    {
      "description": "[InputMapping_data] Input sensitivity multiplier",
      "isPersistent": true,
      "key": "inputSensitivity",
      "type": "Float",
      "value": 1
    },
    {
      "description": "[GridSettings_data] Grid system enabled",
      "isPersistent": true,
      "key": "gridEnabled",
      "type": "Bool",
      "value": false
    },
    {
      "description": "[GridSettings_data] Grid projection type (Ortho/Iso/Hex)",
      "isPersistent": true,
      "key": "gridProjection",
      "type": "String",
      "value": "Ortho"
    },
    {
      "description": "[GridSettings_data] Grid cell size",
      "isPersistent": true,
      "key": "gridCellSize",
      "type": "Vector",
      "value": {
        "x": 32,
        "y": 32,
        "z": 0
      }
    },
    {
      "description": "[GridSettings_data] Hexagon grid radius",
      "isPersistent": true,
      "key": "gridHexRadius",
      "type": "Float",
      "value": 16
    },
    {
      "description": "[GridSettings_data] Grid line color red component",
      "isPersistent": true,
      "key": "gridColorR",
      "type": "Int",
      "value": 180
    },
    {
      "description": "[GridSettings_data] Grid line color green component",
      "isPersistent": true,
      "key": "gridColorG",
      "type": "Int",
      "value": 180
    },
    {
      "description": "[GridSettings_data] Grid line color blue component",
      "isPersistent": true,
      "key": "gridColorB",
      "type": "Int",
      "value": 180
    },
    {
      "description": "[GridSettings_data] Grid line color alpha component",
      "isPersistent": true,
      "key": "gridColorA",
      "type": "Int",
      "value": 255
    },
    {
      "description": "[GridSettings_data] Maximum grid lines to render",
      "isPersistent": true,
      "key": "gridMaxLines",
      "type": "Int",
      "value": 1200
    },
    {
      "description": "[GridSettings_data] LOD zoom threshold for grid LOD",
      "isPersistent": true,
      "key": "gridLODZoomThreshold",
      "type": "Float",
      "value": 0.5
    },
    {
      "description": "[GridSettings_data] Grid LOD skip factor",
      "isPersistent": true,
      "key": "gridLODSkipFactor",
      "type": "Int",
      "value": 10
    },
    {
      "description": "[GridSettings_data] Show collision overlay on grid",
      "isPersistent": false,
      "key": "gridShowCollisionOverlay",
      "type": "Bool",
      "value": false
    },
    {
      "description": "[GridSettings_data] Show navigation overlay on grid",
      "isPersistent": false,
      "key": "gridShowNavigationOverlay",
      "type": "Bool",
      "value": false
    },
    {
      "description": "[GridSettings_data] Active collision layer index",
      "isPersistent": false,
      "key": "gridActiveCollisionLayer",
      "type": "Int",
      "value": 0
    },
    {
      "description": "[GridSettings_data] Active navigation layer index",
      "isPersistent": false,
      "key": "gridActiveNavigationLayer",
      "type": "Int",
      "value": 0
    },
    {
      "description": "[Camera_data] Camera player ID binding",
      "isPersistent": false,
      "key": "cameraPlayerId",
      "type": "Int",
      "value": -1
    },
    {
      "description": "[Camera_data] Camera type (2D/3D)",
      "isPersistent": true,
      "key": "cameraType",
      "type": "String",
      "value": "2D"
    },
    {
      "description": "[Camera_data] Camera world position",
      "isPersistent": false,
      "key": "cameraPosition",
      "type": "Vector",
      "value": {
        "x": 0,
        "y": 0,
        "z": 0
      }
    },
    {
      "description": "[Camera_data] Camera base offset",
      "isPersistent": false,
      "key": "cameraBaseOffset",
      "type": "Vector",
      "value": {
        "x": 0,
        "y": 0,
        "z": 0
      }
    },
    {
      "description": "[Camera_data] Camera control offset",
      "isPersistent": false,
      "key": "cameraControlOffset",
      "type": "Vector",
      "value": {
        "x": 0,
        "y": 0,
        "z": 0
      }
    },
    {
      "description": "[Camera_data] Current camera zoom level",
      "isPersistent": false,
      "key": "cameraZoom",
      "type": "Float",
      "value": 1
    },
    {
      "description": "[Camera_data] Target camera zoom level",
      "isPersistent": false,
      "key": "cameraTargetZoom",
      "type": "Float",
      "value": 1
    },
    {
      "description": "[Camera_data] Camera zoom speed",
      "isPersistent": true,
      "key": "cameraZoomSpeed",
      "type": "Float",
      "value": 5
    },
    {
      "description": "[Camera_data] Minimum camera zoom level",
      "isPersistent": true,
      "key": "cameraMinZoom",
      "type": "Float",
      "value": 0.1
    },
    {
      "description": "[Camera_data] Maximum camera zoom level",
      "isPersistent": true,
      "key": "cameraMaxZoom",
      "type": "Float",
      "value": 5
    },
    {
      "description": "[Camera_data] Current zoom level preset index",
      "isPersistent": false,
      "key": "cameraCurrentZoomLevelIndex",
      "type": "Int",
      "value": 3
    },
    {
      "description": "[Camera_data] Current camera rotation angle",
      "isPersistent": false,
      "key": "cameraRotation",
      "type": "Float",
      "value": 0
    },
    {
      "description": "[Camera_data] Target camera rotation angle",
      "isPersistent": false,
      "key": "cameraTargetRotation",
      "type": "Float",
      "value": 0
    },
    {
      "description": "[Camera_data] Camera rotation speed",
      "isPersistent": true,
      "key": "cameraRotationSpeed",
      "type": "Float",
      "value": 5
    },
    {
      "description": "[Camera_data] Current rotation level preset",
      "isPersistent": false,
      "key": "cameraCurrentRotationLevel",
      "type": "Int",
      "value": 0
    },
    {
      "description": "[Camera_data] Camera control mode (Free/Follow/Fixed)",
      "isPersistent": true,
      "key": "cameraControlMode",
      "type": "String",
      "value": "Free"
    },
    {
      "description": "[Camera_data] Viewport X coordinate",
      "isPersistent": true,
      "key": "cameraViewportX",
      "type": "Float",
      "value": 0
    },
    {
      "description": "[Camera_data] Viewport Y coordinate",
      "isPersistent": true,
      "key": "cameraViewportY",
      "type": "Float",
      "value": 0
    },
    {
      "description": "[Camera_data] Viewport width in pixels",
      "isPersistent": true,
      "key": "cameraViewportWidth",
      "type": "Float",
      "value": 800
    },
    {
      "description": "[Camera_data] Viewport height in pixels",
      "isPersistent": true,
      "key": "cameraViewportHeight",
      "type": "Float",
      "value": 600
    },
    {
      "description": "[Camera_data] Manual camera movement speed",
      "isPersistent": true,
      "key": "cameraManualMoveSpeed",
      "type": "Float",
      "value": 200
    },
    {
      "description": "[Camera_data] Zoom step for keyboard control",
      "isPersistent": true,
      "key": "cameraZoomStep",
      "type": "Float",
      "value": 0.1
    },
    {
      "description": "[Camera_data] Rotation step for keyboard control",
      "isPersistent": true,
      "key": "cameraRotationStep",
      "type": "Float",
      "value": 15
    },
    {
      "description": "[Camera_data] Camera active state",
      "isPersistent": false,
      "key": "cameraIsActive",
      "type": "Bool",
      "value": true
    },
    {
      "description": "[CameraTarget_data] Entity ID for camera to follow",
      "isPersistent": false,
      "key": "cameraTargetEntityID",
      "type": "Int",
      "value": -1
    },
    {
      "description": "[CameraTarget_data] Enable camera follow target",
      "isPersistent": true,
      "key": "cameraFollowTarget",
      "type": "Bool",
      "value": false
    },
    {
      "description": "[CameraTarget_data] Camera follow smoothing factor",
      "isPersistent": true,
      "key": "cameraSmoothFactor",
      "type": "Float",
      "value": 5
    },
    {
      "description": "[CameraTarget_data] Follow offset relative to target",
      "isPersistent": false,
      "key": "cameraFollowOffset",
      "type": "Vector",
      "value": {
        "x": 0,
        "y": 0,
        "z": 0
      }
    },
    {
      "description": "[CameraTarget_data] Allow manual control during follow",
      "isPersistent": true,
      "key": "cameraAllowManualControl",
      "type": "Bool",
      "value": true
    },
    {
      "description": "[CameraTarget_data] Manual control input decay",
      "isPersistent": true,
      "key": "cameraManualControlDecay",
      "type": "Float",
      "value": 2
    },
    {
      "description": "[CameraEffects_data] Camera shake active state",
      "isPersistent": false,
      "key": "cameraIsShaking",
      "type": "Bool",
      "value": false
    },
    {
      "description": "[CameraEffects_data] Camera shake intensity",
      "isPersistent": false,
      "key": "cameraShakeIntensity",
      "type": "Float",
      "value": 0
    },
    {
      "description": "[CameraEffects_data] Camera shake total duration",
      "isPersistent": false,
      "key": "cameraShakeDuration",
      "type": "Float",
      "value": 0
    },
    {
      "description": "[CameraEffects_data] Camera shake remaining time",
      "isPersistent": false,
      "key": "cameraShakeTimeRemaining",
      "type": "Float",
      "value": 0
    },
    {
      "description": "[CameraEffects_data] Camera shake offset vector",
      "isPersistent": false,
      "key": "cameraShakeOffset",
      "type": "Vector",
      "value": {
        "x": 0,
        "y": 0,
        "z": 0
      }
    },
    {
      "description": "[CameraBounds_data] Enable camera boundary constraints",
      "isPersistent": true,
      "key": "cameraUseBounds",
      "type": "Bool",
      "value": false
    },
    {
      "description": "[CameraBounds_data] Camera bounds X coordinate",
      "isPersistent": true,
      "key": "cameraBoundsX",
      "type": "Float",
      "value": 0
    },
    {
      "description": "[CameraBounds_data] Camera bounds Y coordinate",
      "isPersistent": true,
      "key": "cameraBoundsY",
      "type": "Float",
      "value": 0
    },
    {
      "description": "[CameraBounds_data] Camera bounds width",
      "isPersistent": true,
      "key": "cameraBoundsWidth",
      "type": "Float",
      "value": 0
    },
    {
      "description": "[CameraBounds_data] Camera bounds height",
      "isPersistent": true,
      "key": "cameraBoundsHeight",
      "type": "Float",
      "value": 0
    },
    {
      "description": "[CameraBounds_data] Clamp camera to viewport bounds",
      "isPersistent": true,
      "key": "cameraClampToViewport",
      "type": "Bool",
      "value": true
    },
    {
      "description": "[CameraInputBinding_data] Input player ID",
      "isPersistent": true,
      "key": "cameraInputPlayerId",
      "type": "Int",
      "value": -1
    },
    {
      "description": "[CameraInputBinding_data] Input joystick ID",
      "isPersistent": true,
      "key": "cameraInputJoystickId",
      "type": "Int",
      "value": 0
    },
    {
      "description": "[CameraInputBinding_data] Use keyboard for camera control",
      "isPersistent": true,
      "key": "cameraInputUseKeyboard",
      "type": "Bool",
      "value": false
    },
    {
      "description": "[CameraInputBinding_data] Camera input deadzone",
      "isPersistent": true,
      "key": "cameraInputDeadzone",
      "type": "Float",
      "value": 0.15
    },
    {
      "description": "[CameraInputBinding_data] Camera trigger threshold",
      "isPersistent": true,
      "key": "cameraInputTriggerThreshold",
      "type": "Float",
      "value": 0.3
    },
    {
      "description": "[CameraInputBinding_data] Camera input direction",
      "isPersistent": false,
      "key": "cameraInputDirection",
      "type": "Vector",
      "value": {
        "x": 0,
        "y": 0,
        "z": 0
      }
    },
    {
      "description": "[CameraInputBinding_data] Camera rotation input",
      "isPersistent": false,
      "key": "cameraInputRotation",
      "type": "Float",
      "value": 0
    },
    {
      "description": "[CameraInputBinding_data] Camera zoom input",
      "isPersistent": false,
      "key": "cameraInputZoom",
      "type": "Float",
      "value": 0
    },
    {
      "description": "[CameraInputBinding_data] Reset camera position requested",
      "isPersistent": false,
      "key": "cameraInputResetRequested",
      "type": "Bool",
      "value": false
    },
    {
      "description": "[CollisionZone_data] Collision zone X coordinate",
      "isPersistent": false,
      "key": "collisionZoneX",
      "type": "Float",
      "value": 0
    },
    {
      "description": "[CollisionZone_data] Collision zone Y coordinate",
      "isPersistent": false,
      "key": "collisionZoneY",
      "type": "Float",
      "value": 0
    },
    {
      "description": "[CollisionZone_data] Collision zone width",
      "isPersistent": false,
      "key": "collisionZoneWidth",
      "type": "Float",
      "value": 100
    },
    {
      "description": "[CollisionZone_data] Collision zone height",
      "isPersistent": false,
      "key": "collisionZoneHeight",
      "type": "Float",
      "value": 100
    },
    {
      "description": "[CollisionZone_data] Collision zone is static",
      "isPersistent": true,
      "key": "collisionZoneIsStatic",
      "type": "Bool",
      "value": true
    },
    {
      "description": "[NavigationAgent_data] Navigation agent radius",
      "isPersistent": true,
      "key": "navAgentRadius",
      "type": "Float",
      "value": 16
    },
    {
      "description": "[NavigationAgent_data] Navigation agent max speed",
      "isPersistent": true,
      "key": "navAgentMaxSpeed",
      "type": "Float",
      "value": 100
    },
    {
      "description": "[NavigationAgent_data] Navigation arrival distance threshold",
      "isPersistent": true,
      "key": "navAgentArrivalThreshold",
      "type": "Float",
      "value": 5
    },
    {
      "description": "[NavigationAgent_data] Navigation layer mask",
      "isPersistent": true,
      "key": "navAgentLayerMask",
      "type": "Int",
      "value": 1
    },
    {
      "description": "[NavigationAgent_data] Current waypoint index",
      "isPersistent": false,
      "key": "navAgentCurrentWaypointIndex",
      "type": "Int",
      "value": 0
    },
    {
      "description": "[NavigationAgent_data] Target position for navigation",
      "isPersistent": false,
      "key": "navAgentTargetPosition",
      "type": "Vector",
      "value": {
        "x": 0,
        "y": 0,
        "z": 0
      }
    },
    {
      "description": "[NavigationAgent_data] Navigation path found",
      "isPersistent": false,
      "key": "navAgentHasPath",
      "type": "Bool",
      "value": false
    },
    {
      "description": "[NavigationAgent_data] Navigation path needs recalculation",
      "isPersistent": false,
      "key": "navAgentNeedsRepath",
      "type": "Bool",
      "value": false
    },
    {
      "description": "[NavigationAgent_data] Navigation steering weight",
      "isPersistent": false,
      "key": "navAgentSteeringWeight",
      "type": "Float",
      "value": 1
    },
    {
      "description": "[NavigationAgent_data] Avoid obstacles during navigation",
      "isPersistent": true,
      "key": "navAgentAvoidObstacles",
      "type": "Bool",
      "value": true
    },
    {
      "description": "[EditorContext_st] Editor dirty state flag",
      "isPersistent": false,
      "key": "editorIsDirty",
      "type": "Bool",
      "value": false
    },
    {
      "description": "[EditorContext_st] Editor frame delta time",
      "isPersistent": false,
      "key": "editorDeltaTime",
      "type": "Float",
      "value": 0
    }
  ]
}